tookits-0.2.7.dist-info/METADATA
tookits-0.2.7.dist-info/WHEEL
tookits-0.2.7.dist-info/entry_points.txt
tookits/3des/3des.py
tookits/3des/__init__.py
tookits/__init__.py
tookits/basic/__init__.py
tookits/basic/list_helper.py
tookits/config/__init__.py
tookits/config/config_demo.py
tookits/databases/__init__.py
tookits/databases/database_client_util.py
tookits/databases/es_client.py
tookits/databases/hive_client.py
tookits/databases/hive_cmd.py
tookits/databases/hive_helper.py
tookits/databases/redis_mgmt.py
tookits/databases/sql_helper.py
tookits/databases/sqlalchemy_helper.py
tookits/databases/status_check.py
tookits/db_query_demo.py
tookits/libs_core/__init__.py
tookits/libs_core/config_groups_helper.py
tookits/libs_core/config_helper.py
tookits/libs_core/env_prepare.py
tookits/libs_core/load_module.py
tookits/libs_core/mysql_helper.py
tookits/network/__init__.py
tookits/network/ip_helper.py
tookits/network/pdi_helper.py
tookits/network/send_mail.py
tookits/system/__init__.py
tookits/system/aes_cipher.py
tookits/system/basic_utils.py
tookits/system/collections_helper.py
tookits/system/crpyt_helper.py
tookits/system/dict2xml.py
tookits/system/dict_helper.py
tookits/system/excel_helper.py
tookits/system/file_helper.py
tookits/system/load_module.py
tookits/system/priority_tasks.py
tookits/system/process_monitor/__init__.py
tookits/system/process_monitor/process_monitor.py
tookits/system/shell_helper.py
tookits/system/str_helper.py
tookits/system/tasks_deamon/__init__.py
tookits/system/tasks_deamon/tasks_controller.py
tookits/system/tasks_deamon/tasks_multiprocessing.py
tookits/system/tasks_deamon/tasks_process.py
tookits/system/test_shell_helper.py
tookits/system/time_helper.py
tookits/system/win32_env.py
tookits/tookits_app.py
tookits/tookits_cli.py
tookits-0.2.7.dist-info/RECORD
